odoo/addons/sale_product_brand_exception/README.rst
odoo/addons/sale_product_brand_exception/__init__.py
odoo/addons/sale_product_brand_exception/__manifest__.py
odoo/addons/sale_product_brand_exception/data/exception_rule.xml
odoo/addons/sale_product_brand_exception/demo/exception_rule.xml
odoo/addons/sale_product_brand_exception/i18n/es.po
odoo/addons/sale_product_brand_exception/i18n/sale_product_brand_exception.pot
odoo/addons/sale_product_brand_exception/models/__init__.py
odoo/addons/sale_product_brand_exception/models/product_brand.py
odoo/addons/sale_product_brand_exception/models/sale_order.py
odoo/addons/sale_product_brand_exception/readme/CONTRIBUTORS.rst
odoo/addons/sale_product_brand_exception/readme/DESCRIPTION.rst
odoo/addons/sale_product_brand_exception/static/description/icon.png
odoo/addons/sale_product_brand_exception/static/description/index.html
odoo/addons/sale_product_brand_exception/tests/__init__.py
odoo/addons/sale_product_brand_exception/tests/test_product_brand.py
odoo/addons/sale_product_brand_exception/views/product_brand_view.xml
odoo14_addon_sale_product_brand_exception-14.0.1.0.1.dev8.dist-info/METADATA
odoo14_addon_sale_product_brand_exception-14.0.1.0.1.dev8.dist-info/WHEEL
odoo14_addon_sale_product_brand_exception-14.0.1.0.1.dev8.dist-info/top_level.txt
odoo14_addon_sale_product_brand_exception-14.0.1.0.1.dev8.dist-info/RECORD
